lineage_suggestion_agent/__init__.py
lineage_suggestion_agent/agent.py
lineage_suggestion_agent/config.py
lineage_suggestion_agent/constants.py
lineage_suggestion_agent/models.py
lineage_suggestion_agent-0.1.2.dist-info/licenses/LICENSE
lineage_suggestion_agent-0.1.2.dist-info/METADATA
lineage_suggestion_agent-0.1.2.dist-info/WHEEL
lineage_suggestion_agent-0.1.2.dist-info/top_level.txt
lineage_suggestion_agent-0.1.2.dist-info/RECORD
