Metadata-Version: 2.4
Name: lineage-suggestion-agent
Version: 0.1.2
Summary: Add your description here
Requires-Python: >=3.11
License-File: LICENSE
Requires-Dist: sfn-blueprint>=0.7.4
Requires-Dist: pandas
Requires-Dist: pydantic-settings
Provides-Extra: dev
Requires-Dist: pytest>=7.0.0; extra == "dev"
Requires-Dist: pytest-cov>=4.0.0; extra == "dev"
Requires-Dist: black>=23.0.0; extra == "dev"
Requires-Dist: flake8>=6.0.0; extra == "dev"
Requires-Dist: mypy>=1.0.0; extra == "dev"
Dynamic: license-file
